{"votes":[],"title":"Relating to access by a public institution of higher education to the criminal history record information of certain persons seeking to reside in on-campus housing.","alternate_titles":[],"versions":[{"mimetype":"text/html","url":"http://www.legis.state.tx.us/tlodocs/83R/billtext/html/HB00895I.HTM","doc_id":"TXD00051917","name":"Introduced"},{"mimetype":"text/html","url":"http://www.legis.state.tx.us/tlodocs/83R/billtext/html/HB00895H.HTM","doc_id":"TXD00073540","name":"House Committee Report"},{"mimetype":"text/html","url":"http://www.legis.state.tx.us/tlodocs/83R/analysis/html/HB00895H.HTM","doc_id":"TXD00073541","name":"House Committee Report"},{"mimetype":"text/html","url":"http://www.legis.state.tx.us/tlodocs/83R/fiscalNotes/html/HB00895I.HTM","doc_id":"TXD00062195","name":"Introduced"},{"mimetype":"text/html","url":"ftp://ftp.legis.state.tx.us/bills/83R/billtext/html/house_bills/HB00800_HB00899/HB00895H.htm","doc_id":"TXD00072392","name":"HB00895H"},{"mimetype":"text/html","url":"ftp://ftp.legis.state.tx.us/bills/83R/billtext/html/house_bills/HB00800_HB00899/HB00895I.htm","doc_id":"TXD00051918","name":"HB00895I"}],"actions":[{"related_entities":[],"actor":"lower","action":"Filed","date":"2013-02-01 00:00:00","+action_number":"H001","type":["bill:filed"]},{"related_entities":[],"actor":"lower","action":"Read first time","date":"2013-02-19 00:00:00","+action_number":"H005","type":["bill:introduced","bill:reading:1"]},{"related_entities":[{"type":"committee","name":"Higher Education","id":"TXC000011"}],"actor":"lower","action":"Referred to Higher Education","date":"2013-02-19 00:00:00","+action_number":"H070","type":["committee:referred"]},{"related_entities":[],"actor":"lower","action":"Considered in public hearing","date":"2013-03-06 00:00:00","+action_number":"H215","type":["other"]},{"related_entities":[],"actor":"lower","action":"Testimony taken/registration(s) recorded in committee","date":"2013-03-06 00:00:00","+action_number":"H240","type":["other"]},{"related_entities":[],"actor":"lower","action":"Left pending in committee","date":"2013-03-06 00:00:00","+action_number":"H245","type":["other"]},{"related_entities":[],"actor":"lower","action":"Considered in public hearing","date":"2013-04-03 00:00:00","+action_number":"H215","type":["other"]},{"related_entities":[],"actor":"lower","action":"Reported favorably w/o amendment(s)","date":"2013-04-03 00:00:00","+action_number":"H250","type":["committee:passed"]},{"related_entities":[],"actor":"lower","action":"Comte report filed with Committee Coordinator","date":"2013-04-04 00:00:00","+action_number":"H853","type":["other"]},{"related_entities":[],"actor":"lower","action":"Committee report distributed","date":"2013-04-04 00:00:00","+action_number":"H855","type":["other"]},{"related_entities":[],"actor":"lower","action":"Committee report sent to Calendars","date":"2013-04-05 00:00:00","+action_number":"H400","type":["other"]},{"related_entities":[],"actor":"lower","action":"Considered in Calendars","date":"2013-04-29 00:00:00","+action_number":"H415","type":["other"]},{"related_entities":[],"actor":"lower","action":"Considered in Calendars","date":"2013-05-06 00:00:00","+action_number":"H415","type":["other"]},{"related_entities":[],"actor":"lower","action":"Placed on General State Calendar","date":"2013-05-08 00:00:00","+action_number":"H435","type":["other"]}],"scraped_subjects":["Crimes--Miscellaneous (I0200)","Education--Higher--Admission & Attendance (I0257)","Education--Higher--Faculty (I0236)","CRIMINAL RECORDS (S0008)"],"action_dates":{"passed_upper":null,"passed_lower":null,"last":"2013-05-08 00:00:00","signed":null,"first":"2013-02-01 00:00:00"},"chamber":"lower","type":["bill"],"id":"TXB00024918","bill_id":"HB 895"}