{"votes":[],"title":"Relating to authorizing a school district to establish a higher education scholarship endowment; authorizing a tax.","alternate_titles":[],"versions":[{"mimetype":"text/html","url":"http://www.legis.state.tx.us/tlodocs/83R/billtext/html/SB01616I.HTM","doc_id":"TXD00061534","name":"Introduced"},{"mimetype":"text/html","url":"ftp://ftp.legis.state.tx.us/bills/83R/billtext/html/senate_bills/SB01600_SB01699/SB01616I.htm","doc_id":"TXD00061535","name":"SB01616I"}],"actions":[{"related_entities":[],"actor":"upper","date":"2013-03-08 00:00:00","action":"Received by the Secretary of the Senate","+action_number":"S000","type":["bill:filed"]},{"related_entities":[],"actor":"upper","date":"2013-03-08 00:00:00","action":"Filed","+action_number":"S001","type":["bill:filed"]},{"related_entities":[],"actor":"upper","date":"2013-03-20 00:00:00","action":"Read first time","+action_number":"S005","type":["bill:introduced","bill:reading:1"]},{"related_entities":[{"type":"committee","name":"Education","id":"TXC000036"}],"actor":"upper","date":"2013-03-20 00:00:00","action":"Referred to Education","+action_number":"S050","type":["committee:referred"]}],"scraped_subjects":["Education--Higher--Student Financial Aid (I0235)","Education--Primary & Secondary--Finance (I0250)","Education--School Districts (I0220)","Taxation--School District (I0785)"],"action_dates":{"passed_upper":null,"passed_lower":null,"last":"2013-03-20 00:00:00","signed":null,"first":"2013-03-08 00:00:00"},"chamber":"upper","type":["bill"],"id":"TXB00028754","bill_id":"SB 1616"}