{"votes":[],"title":"Relating to higher education for veterans and their families.","alternate_titles":[],"versions":[{"mimetype":"text/html","url":"http://www.legis.state.tx.us/tlodocs/83R/billtext/html/HB03544I.HTM","doc_id":"TXD00064253","name":"Introduced"},{"mimetype":"text/html","url":"http://www.legis.state.tx.us/tlodocs/83R/billtext/html/HB03544H.HTM","doc_id":"TXD00089823","name":"House Committee Report"},{"mimetype":"text/html","url":"http://www.legis.state.tx.us/tlodocs/83R/analysis/html/HB03544H.HTM","doc_id":"TXD00089824","name":"House Committee Report"},{"mimetype":"text/html","url":"http://www.legis.state.tx.us/tlodocs/83R/fiscalNotes/html/HB03544I.HTM","doc_id":"TXD00070422","name":"Introduced"},{"mimetype":"text/html","url":"http://www.legis.state.tx.us/tlodocs/83R/fiscalNotes/html/HB03544H.HTM","doc_id":"TXD00089825","name":"House Committee Report"},{"mimetype":"text/html","url":"ftp://ftp.legis.state.tx.us/bills/83R/billtext/html/house_bills/HB03500_HB03599/HB03544H.htm","doc_id":"TXD00089826","name":"HB03544H"},{"mimetype":"text/html","url":"ftp://ftp.legis.state.tx.us/bills/83R/billtext/html/house_bills/HB03500_HB03599/HB03544I.htm","doc_id":"TXD00064254","name":"HB03544I"}],"actions":[{"related_entities":[],"actor":"lower","date":"2013-03-08 00:00:00","action":"Filed","+action_number":"H001","type":["bill:filed"]},{"related_entities":[],"actor":"lower","date":"2013-03-20 00:00:00","action":"Read first time","+action_number":"H005","type":["bill:introduced","bill:reading:1"]},{"related_entities":[{"type":"committee","name":"Defense & Veterans' Affairs","id":"TXC000058"}],"actor":"lower","date":"2013-03-20 00:00:00","action":"Referred to Defense & Veterans' Affairs","+action_number":"H095","type":["committee:referred"]},{"related_entities":[],"actor":"lower","date":"2013-03-28 00:00:00","action":"Withdrawn from schedule","+action_number":"H210","type":["other"]},{"related_entities":[],"actor":"lower","date":"2013-04-04 00:00:00","action":"Considered in public hearing","+action_number":"H215","type":["other"]},{"related_entities":[],"actor":"lower","date":"2013-04-04 00:00:00","action":"Testimony taken/registration(s) recorded in committee","+action_number":"H240","type":["other"]},{"related_entities":[],"actor":"lower","date":"2013-04-04 00:00:00","action":"Left pending in committee","+action_number":"H245","type":["other"]},{"related_entities":[],"actor":"lower","date":"2013-04-30 00:00:00","action":"Considered in formal meeting","+action_number":"H216","type":["other"]},{"related_entities":[],"actor":"lower","date":"2013-04-30 00:00:00","action":"Committee substitute considered in committee","+action_number":"H241","type":["other"]},{"related_entities":[{"type":"committee","name":"Local & Consent","id":null}],"actor":"lower","date":"2013-04-30 00:00:00","action":"Recommended to be sent to Local & Consent","+action_number":"H255","type":["committee:referred"]},{"related_entities":[],"actor":"lower","date":"2013-04-30 00:00:00","action":"Reported favorably as substituted","+action_number":"H252","type":["committee:passed:favorable"]},{"related_entities":[],"actor":"lower","date":"2013-05-07 00:00:00","action":"Comte report filed with Committee Coordinator","+action_number":"H853","type":["other"]},{"related_entities":[],"actor":"lower","date":"2013-05-07 00:00:00","action":"Committee report distributed","+action_number":"H855","type":["other"]},{"related_entities":[],"actor":"lower","date":"2013-05-08 00:00:00","action":"Comm. report sent to Local & Consent Calendar","+action_number":"H410","type":["other"]}],"chamber":"lower","scraped_subjects":["Education--Higher--Institutions & Programs (I0223)","Education--Higher--Student Financial Aid (I0235)","Education--Higher--Tuition (I0233)","Military & Veterans (I0535)","HIGHER EDUCATION COORDINATING BOARD, TEXAS (V4280)","VETERANS COMMISSION, TEXAS (V0016)"],"action_dates":{"passed_upper":null,"passed_lower":null,"last":"2013-05-08 00:00:00","signed":null,"first":"2013-03-08 00:00:00"},"type":["bill"],"id":"TXB00030033","bill_id":"HB 3544"}