{"votes":[],"title":"Relating to an annual football game between The University of Texas at Austin and Texas A&M University.","alternate_titles":[],"versions":[{"mimetype":"text/html","url":"http://www.legis.state.tx.us/tlodocs/83R/billtext/html/HB00778I.HTM","doc_id":"TXD00051454","name":"Introduced"},{"mimetype":"text/html","url":"ftp://ftp.legis.state.tx.us/bills/83R/billtext/html/house_bills/HB00700_HB00799/HB00778I.htm","doc_id":"TXD00051342","name":"HB00778I"}],"actions":[{"related_entities":[],"actor":"lower","action":"Filed","date":"2013-01-28 00:00:00","+action_number":"H001","type":["bill:filed"]},{"related_entities":[],"actor":"lower","action":"Read first time","date":"2013-02-18 00:00:00","+action_number":"H005","type":["bill:introduced","bill:reading:1"]},{"related_entities":[{"type":"committee","name":"Higher Education","id":"TXC000011"}],"actor":"lower","action":"Referred to Higher Education","date":"2013-02-18 00:00:00","+action_number":"H070","type":["committee:referred"]}],"chamber":"lower","scraped_subjects":["Amusements, Games, Sports (I0034)","Education--Higher--Athletics (I0256)","Education--Higher--Institutions & Programs (I0223)","TEXAS A&M UNIVERSITY (U0030)","UNIVERSITY OF TEXAS AT AUSTIN                                (U0397)"],"action_dates":{"passed_upper":null,"passed_lower":null,"last":"2013-02-18 00:00:00","signed":null,"first":"2013-01-28 00:00:00"},"type":["bill"],"id":"TXB00024664","bill_id":"HB 778"}