{"votes":[],"title":"Relating to cardiac assessments of participants in extracurricular athletic activities sponsored or sanctioned by the University Interscholastic League.","alternate_titles":[],"versions":[{"mimetype":"text/html","url":"http://www.legis.state.tx.us/tlodocs/84R/billtext/html/HB00767I.HTM","doc_id":"TXD00112663","name":"Introduced"},{"mimetype":"text/html","url":"ftp://ftp.legis.state.tx.us/bills/84R/billtext/html/house_bills/HB00700_HB00799/HB00767I.htm","doc_id":"TXD00112664","name":"HB00767I"}],"actions":[{"related_entities":[],"actor":"lower","date":"2015-01-16 00:00:00","action":"Filed","+action_number":"H001","type":["bill:filed"]}],"scraped_subjects":["Amusements, Games, Sports (I0034)","Education--Primary & Secondary--Extracurricular Activities (I0247)","Education--School Districts (I0220)","Minors--Health & Safety (I0533)","UNIVERSITY INTERSCHOLASTIC LEAGUE (S0337)"],"action_dates":{"passed_upper":null,"passed_lower":null,"last":"2015-01-16 00:00:00","signed":null,"first":"2015-01-16 00:00:00"},"chamber":"lower","type":["bill"],"id":"TXB00036180","bill_id":"HB 767"}