{"votes":[],"title":"Relating to the public transportation advisory committee.","alternate_titles":[],"versions":[{"mimetype":"text/html","url":"http://www.legis.state.tx.us/tlodocs/84R/billtext/html/HB00499I.HTM","doc_id":"TXD00110891","name":"Introduced"},{"mimetype":"text/html","url":"ftp://ftp.legis.state.tx.us/bills/84R/billtext/html/house_bills/HB00400_HB00499/HB00499I.htm","doc_id":"TXD00110892","name":"HB00499I"}],"actions":[{"related_entities":[],"actor":"lower","date":"2014-12-12 00:00:00","action":"Filed","+action_number":"H001","type":["bill:filed"]}],"scraped_subjects":["Transportation--Miscellaneous (I0824)","PUBLIC TRANSPORTATION ADVISORY COMMITTEE (V0823)"],"action_dates":{"passed_upper":null,"passed_lower":null,"last":"2014-12-12 00:00:00","signed":null,"first":"2014-12-12 00:00:00"},"chamber":"lower","type":["bill"],"id":"TXB00035304","bill_id":"HB 499"}