{"votes":[],"title":"Relating to the penalty for theft of an official ballot or official carrier envelope for an election.","alternate_titles":[],"versions":[{"mimetype":"text/html","url":"http://www.legis.state.tx.us/tlodocs/84R/billtext/html/SB00120I.HTM","doc_id":"TXD00111059","name":"Introduced"},{"mimetype":"text/html","url":"ftp://ftp.legis.state.tx.us/bills/84R/billtext/html/senate_bills/SB00100_SB00199/SB00120I.htm","doc_id":"TXD00111060","name":"SB00120I"}],"actions":[{"related_entities":[],"actor":"upper","date":"2014-11-10 00:00:00","action":"Received by the Secretary of the Senate","+action_number":"S000","type":["bill:filed"]},{"related_entities":[],"actor":"upper","date":"2014-11-10 00:00:00","action":"Filed","+action_number":"S001","type":["bill:filed"]}],"scraped_subjects":["Crimes--Miscellaneous (I0200)","Criminal Procedure--Sentencing & Punishment (I0205)","Elections--Administration (I0277)"],"action_dates":{"passed_upper":null,"passed_lower":null,"last":"2014-11-10 00:00:00","signed":null,"first":"2014-11-10 00:00:00"},"chamber":"upper","type":["bill"],"id":"TXB00035388","bill_id":"SB 120"}