{"votes":[],"title":"Relating to an exemption from the motor vehicle sales and use tax for certain military servicemembers serving on active duty.","alternate_titles":[],"versions":[{"mimetype":"text/html","url":"http://www.legis.state.tx.us/tlodocs/84R/billtext/html/HB00682I.HTM","doc_id":"TXD00112362","name":"Introduced"},{"mimetype":"text/html","url":"ftp://ftp.legis.state.tx.us/bills/84R/billtext/html/house_bills/HB00600_HB00699/HB00682I.htm","doc_id":"TXD00112363","name":"HB00682I"}],"actions":[{"related_entities":[],"actor":"lower","date":"2015-01-13 00:00:00","action":"Filed","+action_number":"H001","type":["bill:filed"]}],"scraped_subjects":["Military & Veterans (I0535)","Taxation--Sales (I0800)","Vehicles & Traffic--General (I0865)"],"action_dates":{"passed_upper":null,"passed_lower":null,"last":"2015-01-13 00:00:00","signed":null,"first":"2015-01-13 00:00:00"},"chamber":"lower","type":["bill"],"id":"TXB00036040","bill_id":"HB 682"}