{"votes":[],"title":"Relating to the carrying of concealed handguns on the campuses of and certain other locations associated with institutions of higher education.","alternate_titles":[],"versions":[{"mimetype":"text/html","url":"http://www.legis.state.tx.us/tlodocs/83R/billtext/html/SB00182I.HTM","doc_id":"TXD00050418","name":"Introduced"},{"mimetype":"text/html","url":"ftp://ftp.legis.state.tx.us/bills/83R/billtext/html/senate_bills/SB00100_SB00199/SB00182I.htm","doc_id":"TXD00050419","name":"SB00182I"}],"actions":[{"related_entities":[],"actor":"upper","date":"2013-01-17 00:00:00","action":"Received by the Secretary of the Senate","+action_number":"S000","type":["bill:filed"]},{"related_entities":[],"actor":"upper","date":"2013-01-17 00:00:00","action":"Filed","+action_number":"S001","type":["bill:filed"]},{"related_entities":[],"actor":"upper","date":"2013-01-29 00:00:00","action":"Read first time","+action_number":"S005","type":["bill:introduced","bill:reading:1"]},{"related_entities":[{"type":"committee","name":"Criminal Justice","id":"TXC000051"}],"actor":"upper","date":"2013-01-29 00:00:00","action":"Referred to Criminal Justice","+action_number":"S030","type":["committee:referred"]}],"chamber":"upper","scraped_subjects":["Education--Higher--Institutions & Programs (I0223)","Weapons (I0887)","CONCEALED HANDGUNS (S0241)"],"action_dates":{"passed_upper":null,"passed_lower":null,"last":"2013-01-29 00:00:00","signed":null,"first":"2013-01-17 00:00:00"},"type":["bill"],"id":"TXB00024210","bill_id":"SB 182"}