{"votes":[],"title":"Relating to the punishment for the offense of burglary of a vehicle and to grants of community supervision to persons who commit that offense.","alternate_titles":[],"versions":[{"mimetype":"text/html","url":"http://www.legis.state.tx.us/tlodocs/84R/billtext/html/HB00381I.HTM","doc_id":"TXD00110639","name":"Introduced"},{"mimetype":"text/html","url":"ftp://ftp.legis.state.tx.us/bills/84R/billtext/html/house_bills/HB00300_HB00399/HB00381I.htm","doc_id":"TXD00110640","name":"HB00381I"}],"actions":[{"related_entities":[],"actor":"lower","date":"2014-11-25 00:00:00","action":"Filed","+action_number":"H001","type":["bill:filed"]}],"scraped_subjects":["Crimes--Against Property (I0175)","Criminal Procedure--Sentencing & Punishment (I0205)","BURGLARY (S0570)","MANDATORY & COMMUNITY SUPERVISION (S2314)"],"action_dates":{"passed_upper":null,"passed_lower":null,"last":"2014-11-25 00:00:00","signed":null,"first":"2014-11-25 00:00:00"},"chamber":"lower","type":["bill"],"id":"TXB00035178","bill_id":"HB 381"}