{"votes":[],"title":"Relating to accelerated educational programs offered by public institutions of higher education to qualified persons seeking licensure as physician assistants.","alternate_titles":[],"versions":[{"mimetype":"text/html","url":"http://www.legis.state.tx.us/tlodocs/83R/billtext/html/SB01674I.HTM","doc_id":"TXD00061650","name":"Introduced"},{"mimetype":"text/html","url":"ftp://ftp.legis.state.tx.us/bills/83R/billtext/html/senate_bills/SB01600_SB01699/SB01674I.htm","doc_id":"TXD00061651","name":"SB01674I"}],"actions":[{"related_entities":[],"actor":"upper","date":"2013-03-08 00:00:00","action":"Received by the Secretary of the Senate","+action_number":"S000","type":["bill:filed"]},{"related_entities":[],"actor":"upper","date":"2013-03-08 00:00:00","action":"Filed","+action_number":"S001","type":["bill:filed"]},{"related_entities":[],"actor":"upper","date":"2013-03-25 00:00:00","action":"Read first time","+action_number":"S005","type":["bill:introduced","bill:reading:1"]},{"related_entities":[{"type":"committee","name":"Higher Education","id":"TXC000029"}],"actor":"upper","date":"2013-03-25 00:00:00","action":"Referred to Higher Education","+action_number":"S068","type":["committee:referred"]}],"scraped_subjects":["Education--Higher--General (I0231)","Education--Higher--Health Institutions (I0237)","Education--Higher--Institutions & Programs (I0223)","Military & Veterans (I0535)","PHYSICIAN ASSISTANTS (S0081)","HIGHER EDUCATION COORDINATING BOARD, TEXAS (V4280)"],"action_dates":{"passed_upper":null,"passed_lower":null,"last":"2013-03-25 00:00:00","signed":null,"first":"2013-03-08 00:00:00"},"chamber":"upper","type":["bill"],"id":"TXB00028812","bill_id":"SB 1674"}