{"votes":[],"title":"Relating to the criteria for awarding the Texas Purple Heart Medal to members of the armed forces wounded or killed at Fort Hood on November 5, 2009.","alternate_titles":[],"versions":[{"mimetype":"text/html","url":"http://www.legis.state.tx.us/tlodocs/84R/billtext/html/HB00115I.HTM","doc_id":"TXD00111007","name":"Introduced"},{"mimetype":"text/html","url":"ftp://ftp.legis.state.tx.us/bills/84R/billtext/html/house_bills/HB00100_HB00199/HB00115I.htm","doc_id":"TXD00111008","name":"HB00115I"}],"actions":[{"related_entities":[],"actor":"lower","action":"Filed","date":"2014-11-10 00:00:00","+action_number":"H001","type":["bill:filed"]}],"chamber":"lower","scraped_subjects":["Military & Veterans (I0535)","AWARDS, MEDALS, PRIZES (S0129)"],"action_dates":{"passed_upper":null,"passed_lower":null,"last":"2014-11-10 00:00:00","signed":null,"first":"2014-11-10 00:00:00"},"type":["bill"],"id":"TXB00035362","bill_id":"HB 115"}