{"votes":[],"title":"Relating to the prosecution of murder committed in the course of committing or attempting to commit trafficking of persons.","alternate_titles":[],"versions":[{"mimetype":"text/html","url":"http://www.legis.state.tx.us/tlodocs/84R/billtext/html/HB00112I.HTM","doc_id":"TXD00110345","name":"Introduced"},{"mimetype":"text/html","url":"ftp://ftp.legis.state.tx.us/bills/84R/billtext/html/house_bills/HB00100_HB00199/HB00112I.htm","doc_id":"TXD00110346","name":"HB00112I"}],"actions":[{"related_entities":[],"actor":"lower","date":"2014-11-10 00:00:00","action":"Filed","+action_number":"H001","type":["bill:filed"]}],"scraped_subjects":["Crimes--Against Persons--General (I0170)","Crimes--Capital Punishment (I0195)","HUMAN TRAFFICKING (S0696)"],"action_dates":{"passed_upper":null,"passed_lower":null,"last":"2014-11-10 00:00:00","signed":null,"first":"2014-11-10 00:00:00"},"chamber":"lower","type":["bill"],"id":"TXB00035031","bill_id":"HB 112"}