{"votes":[],"title":"Relating to the investment of funds by the governing boards of certain institutions of higher education.","alternate_titles":[],"versions":[{"mimetype":"text/html","url":"http://www.legis.state.tx.us/tlodocs/83R/billtext/html/HB03353I.HTM","doc_id":"TXD00063902","name":"Introduced"},{"mimetype":"text/html","url":"http://www.legis.state.tx.us/tlodocs/83R/billtext/html/HB03353H.HTM","doc_id":"TXD00080188","name":"House Committee Report"},{"mimetype":"text/html","url":"http://www.legis.state.tx.us/tlodocs/83R/analysis/html/HB03353H.HTM","doc_id":"TXD00080189","name":"House Committee Report"},{"mimetype":"text/html","url":"http://www.legis.state.tx.us/tlodocs/83R/fiscalNotes/html/HB03353I.HTM","doc_id":"TXD00073687","name":"Introduced"},{"mimetype":"text/html","url":"ftp://ftp.legis.state.tx.us/bills/83R/billtext/html/house_bills/HB03300_HB03399/HB03353H.htm","doc_id":"TXD00080190","name":"HB03353H"},{"mimetype":"text/html","url":"ftp://ftp.legis.state.tx.us/bills/83R/billtext/html/house_bills/HB03300_HB03399/HB03353I.htm","doc_id":"TXD00063903","name":"HB03353I"}],"actions":[{"related_entities":[],"actor":"lower","date":"2013-03-08 00:00:00","action":"Filed","+action_number":"H001","type":["bill:filed"]},{"related_entities":[],"actor":"lower","date":"2013-03-19 00:00:00","action":"Read first time","+action_number":"H005","type":["bill:introduced","bill:reading:1"]},{"related_entities":[{"type":"committee","name":"Higher Education","id":"TXC000011"}],"actor":"lower","date":"2013-03-19 00:00:00","action":"Referred to Higher Education","+action_number":"H070","type":["committee:referred"]},{"related_entities":[],"actor":"lower","date":"2013-04-10 00:00:00","action":"Considered in public hearing","+action_number":"H215","type":["other"]},{"related_entities":[],"actor":"lower","date":"2013-04-10 00:00:00","action":"Testimony taken/registration(s) recorded in committee","+action_number":"H240","type":["other"]},{"related_entities":[],"actor":"lower","date":"2013-04-10 00:00:00","action":"Left pending in committee","+action_number":"H245","type":["other"]},{"related_entities":[],"actor":"lower","date":"2013-04-18 00:00:00","action":"Considered in formal meeting","+action_number":"H216","type":["other"]},{"related_entities":[{"type":"committee","name":"Local & Consent","id":null}],"actor":"lower","date":"2013-04-18 00:00:00","action":"Recommended to be sent to Local & Consent","+action_number":"H255","type":["committee:referred"]},{"related_entities":[],"actor":"lower","date":"2013-04-18 00:00:00","action":"Reported favorably w/o amendment(s)","+action_number":"H250","type":["committee:passed"]},{"related_entities":[],"actor":"lower","date":"2013-04-19 00:00:00","action":"Comte report filed with Committee Coordinator","+action_number":"H853","type":["other"]},{"related_entities":[],"actor":"lower","date":"2013-04-21 00:00:00","action":"Committee report distributed","+action_number":"H855","type":["other"]},{"related_entities":[],"actor":"lower","date":"2013-04-22 00:00:00","action":"Comm. report sent to Local & Consent Calendar","+action_number":"H410","type":["other"]},{"related_entities":[],"actor":"lower","date":"2013-05-01 00:00:00","action":"Considered in Local & Consent Calendars","+action_number":"H416","type":["other"]},{"related_entities":[],"actor":"lower","date":"2013-05-02 00:00:00","action":"Placed on Local, Consent, and Res. Calendar","+action_number":"H465","type":["other"]},{"related_entities":[],"actor":"lower","date":"2013-05-02 00:00:00","action":"Companion considered in lieu of","+action_number":"H506","type":["other"],"+comment":"SB 1019"},{"related_entities":[],"actor":"lower","date":"2013-05-02 00:00:00","action":"Laid on the table subject to call","+action_number":"H621","type":["other"]}],"scraped_subjects":["Education--Higher--Finance (I0232)","Education--Higher--Institutions & Programs (I0223)"],"action_dates":{"passed_upper":null,"passed_lower":null,"last":"2013-05-02 00:00:00","signed":null,"first":"2013-03-08 00:00:00"},"chamber":"lower","type":["bill"],"id":"TXB00029842","bill_id":"HB 3353"}