{"votes":[],"title":"Relating to the creation of the offense of unlawful disclosure of certain visual material.","alternate_titles":[],"versions":[{"mimetype":"text/html","url":"http://www.legis.state.tx.us/tlodocs/84R/billtext/html/HB00101I.HTM","doc_id":"TXD00110443","name":"Introduced"},{"mimetype":"text/html","url":"ftp://ftp.legis.state.tx.us/bills/84R/billtext/html/house_bills/HB00100_HB00199/HB00101I.htm","doc_id":"TXD00110444","name":"HB00101I"}],"actions":[{"related_entities":[],"actor":"lower","date":"2014-11-10 00:00:00","action":"Filed","+action_number":"H001","type":["bill:filed"]}],"scraped_subjects":["Crimes--Against Persons--Sexual (I0171)","Crimes--Miscellaneous (I0200)","Criminal Procedure--General (I0208)","INTERNET (S0130)","VIDEOTAPE & FILM (S2361)"],"action_dates":{"passed_upper":null,"passed_lower":null,"last":"2014-11-10 00:00:00","signed":null,"first":"2014-11-10 00:00:00"},"chamber":"lower","type":["bill"],"id":"TXB00035080","bill_id":"HB 101"}