{"votes":[],"title":"Relating to authorizing the issuance of revenue bonds for a clinical sciences building for the El Paso campus of the Texas Tech University Health Sciences Center.","alternate_titles":[],"versions":[{"mimetype":"text/html","url":"http://www.legis.state.tx.us/tlodocs/83R/billtext/html/HB01527I.HTM","doc_id":"TXD00055444","name":"Introduced"},{"mimetype":"text/html","url":"ftp://ftp.legis.state.tx.us/bills/83R/billtext/html/house_bills/HB01500_HB01599/HB01527I.htm","doc_id":"TXD00055445","name":"HB01527I"}],"actions":[{"related_entities":[],"actor":"lower","date":"2013-02-20 00:00:00","action":"Filed","+action_number":"H001","type":["bill:filed"]},{"related_entities":[],"actor":"lower","date":"2013-02-25 00:00:00","action":"Read first time","+action_number":"H005","type":["bill:introduced","bill:reading:1"]},{"related_entities":[{"type":"committee","name":"Higher Education","id":"TXC000011"}],"actor":"lower","date":"2013-02-25 00:00:00","action":"Referred to Higher Education","+action_number":"H070","type":["committee:referred"]}],"scraped_subjects":["Education--Higher--Finance (I0232)","Education--Higher--Health Institutions (I0237)","Education--Higher--Tuition (I0233)","BONDS (S6060)","TEXAS TECH UNIVERSITY HEALTH SCIENCES CENTER AT EL PASO (U0176)"],"action_dates":{"passed_upper":null,"passed_lower":null,"last":"2013-02-25 00:00:00","signed":null,"first":"2013-02-20 00:00:00"},"chamber":"lower","type":["bill"],"id":"TXB00026392","bill_id":"HB 1527"}