{"votes":[],"title":"Relating to the designation of a portion of State Highway 207 in Armstrong County as the Hamblen Memorial Highway.","alternate_titles":[],"versions":[{"mimetype":"text/html","url":"http://www.legis.state.tx.us/tlodocs/84R/billtext/html/HB00663I.HTM","doc_id":"TXD00112325","name":"Introduced"},{"mimetype":"text/html","url":"ftp://ftp.legis.state.tx.us/bills/84R/billtext/html/house_bills/HB00600_HB00699/HB00663I.htm","doc_id":"TXD00112326","name":"HB00663I"}],"actions":[{"related_entities":[],"actor":"lower","action":"Filed","date":"2015-01-12 00:00:00","+action_number":"H001","type":["bill:filed"]}],"chamber":"lower","scraped_subjects":["ARMSTRONG COUNTY (G0303)","Highways (I0390)","HAMBLEN MEMORIAL HIGHWAY (S0788)","TRANSPORTATION, TEXAS DEPARTMENT OF (V8796)"],"action_dates":{"passed_upper":null,"passed_lower":null,"last":"2015-01-12 00:00:00","signed":null,"first":"2015-01-12 00:00:00"},"type":["bill"],"id":"TXB00036021","bill_id":"HB 663"}