{"votes":[],"title":"Relating to creating a criminal offense for a candidate for public office who misrepresents the candidate's residency.","alternate_titles":[],"versions":[{"mimetype":"text/html","url":"http://www.legis.state.tx.us/tlodocs/84R/billtext/html/HB00816I.HTM","doc_id":"TXD00112949","name":"Introduced"},{"mimetype":"text/html","url":"ftp://ftp.legis.state.tx.us/bills/84R/billtext/html/house_bills/HB00800_HB00899/HB00816I.htm","doc_id":"TXD00112950","name":"HB00816I"}],"actions":[{"related_entities":[],"actor":"lower","action":"Filed","date":"2015-01-21 00:00:00","+action_number":"H001","type":["bill:filed"]}],"chamber":"lower","scraped_subjects":["Elections--Candidates (I0280)","Legislature (I0520)","State Officers (I0761)"],"action_dates":{"passed_upper":null,"passed_lower":null,"last":"2015-01-21 00:00:00","signed":null,"first":"2015-01-21 00:00:00"},"type":["bill"],"id":"TXB00036318","bill_id":"HB 816"}