{"votes":[],"title":"Relating to the creation of a task force to evaluate state assessment instruments administered to public school students with significant cognitive disabilities.","alternate_titles":[],"versions":[{"mimetype":"text/html","url":"http://www.legis.state.tx.us/tlodocs/84R/billtext/html/HB00043I.HTM","doc_id":"TXD00110741","name":"Introduced"},{"mimetype":"text/html","url":"ftp://ftp.legis.state.tx.us/bills/84R/billtext/html/house_bills/HB00001_HB00099/HB00043I.htm","doc_id":"TXD00110742","name":"HB00043I"}],"actions":[{"related_entities":[],"actor":"lower","date":"2014-11-10 00:00:00","action":"Filed","+action_number":"H001","type":["bill:filed"]}],"scraped_subjects":["Disabilities, Persons with (I0380)","Education--Primary & Secondary--Accountability (I0007)","Education--Primary & Secondary--Special (I0243)","Education--Primary & Secondary--Testing (I0229)","EDUCATION AGENCY, TEXAS (V9941)"],"action_dates":{"passed_upper":null,"passed_lower":null,"last":"2014-11-10 00:00:00","signed":null,"first":"2014-11-10 00:00:00"},"chamber":"lower","type":["bill"],"id":"TXB00035229","bill_id":"HB 43"}