{"votes":[],"title":"Relating to authorizing the issuance of revenue bonds to fund an interdisciplinary research facility at The University of Texas at El Paso.","alternate_titles":[],"versions":[{"mimetype":"text/html","url":"http://www.legis.state.tx.us/tlodocs/83R/billtext/html/SB01042I.HTM","doc_id":"TXD00058998","name":"Introduced"},{"mimetype":"text/html","url":"ftp://ftp.legis.state.tx.us/bills/83R/billtext/html/senate_bills/SB01000_SB01099/SB01042I.htm","doc_id":"TXD00058999","name":"SB01042I"}],"actions":[{"related_entities":[],"actor":"upper","action":"Received by the Secretary of the Senate","date":"2013-03-04 00:00:00","+action_number":"S000","type":["bill:filed"]},{"related_entities":[],"actor":"upper","action":"Filed","date":"2013-03-04 00:00:00","+action_number":"S001","type":["bill:filed"]},{"related_entities":[],"actor":"upper","action":"Read first time","date":"2013-03-12 00:00:00","+action_number":"S005","type":["bill:introduced","bill:reading:1"]},{"related_entities":[{"type":"committee","name":"Finance","id":"TXC000042"}],"actor":"upper","action":"Referred to Finance","date":"2013-03-12 00:00:00","+action_number":"S060","type":["committee:referred"]}],"scraped_subjects":["Education--Higher--Finance (I0232)","Education--Higher--Institutions & Programs (I0223)","Education--Higher--Tuition (I0233)","BONDS (S6060)","UNIVERSITY OF TEXAS AT EL PASO (U0019)","UNIVERSITY OF TEXAS SYSTEM (U0045)"],"action_dates":{"passed_upper":null,"passed_lower":null,"last":"2013-03-12 00:00:00","signed":null,"first":"2013-03-04 00:00:00"},"chamber":"upper","type":["bill"],"id":"TXB00027679","bill_id":"SB 1042"}